airflow_providers_geonode_op/__init__.py
airflow_providers_geonode_op/operator/__init__.py
airflow_providers_geonode_op/operator/geonode_operator.py
airflow_providers_geonode_op-0.1.7.dist-info/METADATA
airflow_providers_geonode_op-0.1.7.dist-info/WHEEL
airflow_providers_geonode_op-0.1.7.dist-info/top_level.txt
airflow_providers_geonode_op-0.1.7.dist-info/RECORD
