Metadata-Version: 2.1
Name: airflow-providers-geonode-op
Version: 0.1.7
Summary: Custom GeoNode Operator for Apache Airflow
Home-page: UNKNOWN
Author: Kan Territory & IT
Author-email: develop@kan-gl.com
License: MIT
Platform: UNKNOWN
Classifier: Programming Language :: Python :: 3
Classifier: License :: OSI Approved :: MIT License
Classifier: Operating System :: OS Independent
Requires-Dist: requests
Requires-Dist: apache-airflow
